wfmap/__init__.py
wfmap/data.py
wfmap/data/wfdata.csv
wfmap-1.0.3.dist-info/LICENSE
wfmap-1.0.3.dist-info/METADATA
wfmap-1.0.3.dist-info/WHEEL
wfmap-1.0.3.dist-info/top_level.txt
wfmap-1.0.3.dist-info/RECORD
